pptestkarolchrapczynski/__init__.py
pptestkarolchrapczynski/m_mod_pptest.py
pptestkarolchrapczynski-0.0.1.dist-info/LICENCE.txt
pptestkarolchrapczynski-0.0.1.dist-info/METADATA
pptestkarolchrapczynski-0.0.1.dist-info/WHEEL
pptestkarolchrapczynski-0.0.1.dist-info/top_level.txt
pptestkarolchrapczynski-0.0.1.dist-info/RECORD
